{"nodes": [{"id": "celeryapp_celery_app", "label": "Celery App (restaurant)", "file_type": "code", "source_file": "apps/workers/celery_app.py", "source_location": null, "source_url": null, "captured_at": null, "author": null, "contributor": null}, {"id": "celeryapp_beat_schedule", "label": "Celery beat_schedule", "file_type": "code", "source_file": "apps/workers/celery_app.py", "source_location": null, "source_url": null, "captured_at": null, "author": null, "contributor": null}], "edges": [{"source": "celeryapp_celery_app", "target": "config_get_settings", "relation": "calls", "confidence": "EXTRACTED", "confidence_score": 1.0, "source_file": "apps/workers/celery_app.py", "source_location": null, "weight": 1.0}, {"source": "celeryapp_beat_schedule", "target": "config_Settings", "relation": "references", "confidence": "EXTRACTED", "confidence_score": 1.0, "source_file": "apps/workers/celery_app.py", "source_location": null, "weight": 1.0}, {"source": "env_alembic_env", "target": "celeryapp_celery_app", "relation": "shares_data_with", "confidence": "INFERRED", "confidence_score": 0.85, "source_file": "apps/workers/celery_app.py", "source_location": null, "weight": 1.0}], "hyperedges": []}