{"nodes": [{"id": "partnerApi_createApiKey", "label": "createApiKey", "file_type": "code", "source_file": "frontend/src/lib/partnerApi.ts", "source_location": null, "source_url": null, "captured_at": null, "author": null, "contributor": null}, {"id": "partnerApi_revokeApiKey", "label": "revokeApiKey", "file_type": "code", "source_file": "frontend/src/lib/partnerApi.ts", "source_location": null, "source_url": null, "captured_at": null, "author": null, "contributor": null}], "edges": [], "hyperedges": []}