{"nodes": [{"id": "users_syed_files_untitled_folder_2_work_catalystiq_full_pos_system_src_app_idempotency_models_py", "label": "models.py", "file_type": "code", "source_file": "src/app/idempotency/models.py", "source_location": "L1"}, {"id": "idempotency_models_idempotencykey", "label": "IdempotencyKey", "file_type": "code", "source_file": "src/app/idempotency/models.py", "source_location": "L8"}, {"id": "base", "label": "Base", "file_type": "code", "source_file": "", "source_location": ""}, {"id": "timestampmixin", "label": "TimestampMixin", "file_type": "code", "source_file": "", "source_location": ""}, {"id": "idempotency_models_rationale_9", "label": "Dedup record for a replayed mutating request.      Scoped by (restaurant_id, key", "file_type": "rationale", "source_file": "src/app/idempotency/models.py", "source_location": "L9"}], "edges": [{"source": "users_syed_files_untitled_folder_2_work_catalystiq_full_pos_system_src_app_idempotency_models_py", "target": "sqlalchemy", "relation": "imports_from", "context": "import", "confidence": "EXTRACTED", "source_file": "src/app/idempotency/models.py", "source_location": "L2", "weight": 1.0}, {"source": "users_syed_files_untitled_folder_2_work_catalystiq_full_pos_system_src_app_idempotency_models_py", "target": "sqlalchemy_orm", "relation": "imports_from", "context": "import", "confidence": "EXTRACTED", "source_file": "src/app/idempotency/models.py", "source_location": "L3", "weight": 1.0}, {"source": "users_syed_files_untitled_folder_2_work_catalystiq_full_pos_system_src_app_idempotency_models_py", "target": "app_db", "relation": "imports_from", "context": "import", "confidence": "EXTRACTED", "source_file": "src/app/idempotency/models.py", "source_location": "L5", "weight": 1.0}, {"source": "users_syed_files_untitled_folder_2_work_catalystiq_full_pos_system_src_app_idempotency_models_py", "target": "idempotency_models_idempotencykey", "relation": "contains", "confidence": "EXTRACTED", "source_file": "src/app/idempotency/models.py", "source_location": "L8", "weight": 1.0}, {"source": "idempotency_models_idempotencykey", "target": "base", "relation": "inherits", "confidence": "EXTRACTED", "source_file": "src/app/idempotency/models.py", "source_location": "L8", "weight": 1.0}, {"source": "idempotency_models_idempotencykey", "target": "timestampmixin", "relation": "inherits", "confidence": "EXTRACTED", "source_file": "src/app/idempotency/models.py", "source_location": "L8", "weight": 1.0}, {"source": "idempotency_models_rationale_9", "target": "idempotency_models_idempotencykey", "relation": "rationale_for", "confidence": "EXTRACTED", "source_file": "src/app/idempotency/models.py", "source_location": "L9", "weight": 1.0}], "raw_calls": []}