{"nodes": [{"id": "src_app_predictions_port_py", "label": "port.py", "file_type": "code", "source_file": "src/app/predictions/port.py", "source_location": "L1"}, {"id": "port_dishhourforecast", "label": "DishHourForecast", "file_type": "code", "source_file": "src/app/predictions/port.py", "source_location": "L8"}, {"id": "port_forecastmodel", "label": "ForecastModel", "file_type": "code", "source_file": "src/app/predictions/port.py", "source_location": "L17"}, {"id": "protocol", "label": "Protocol", "file_type": "code", "source_file": "", "source_location": ""}, {"id": "port_forecastmodel_fit", "label": ".fit()", "file_type": "code", "source_file": "src/app/predictions/port.py", "source_location": "L22"}, {"id": "port_forecastmodel_predict_dish_hour", "label": ".predict_dish_hour()", "file_type": "code", "source_file": "src/app/predictions/port.py", "source_location": "L24"}, {"id": "port_rationale_18", "label": "Swap seam: RollingAverageModel today; LightGBM/sklearn/prophet later, no call-si", "file_type": "rationale", "source_file": "src/app/predictions/port.py", "source_location": "L18"}], "edges": [{"source": "src_app_predictions_port_py", "target": "dataclasses", "relation": "imports_from", "confidence": "EXTRACTED", "source_file": "src/app/predictions/port.py", "source_location": "L1", "weight": 1.0}, {"source": "src_app_predictions_port_py", "target": "typing", "relation": "imports_from", "confidence": "EXTRACTED", "source_file": "src/app/predictions/port.py", "source_location": "L2", "weight": 1.0}, {"source": "src_app_predictions_port_py", "target": "app_predictions_features", "relation": "imports_from", "confidence": "EXTRACTED", "source_file": "src/app/predictions/port.py", "source_location": "L4", "weight": 1.0}, {"source": "src_app_predictions_port_py", "target": "port_dishhourforecast", "relation": "contains", "confidence": "EXTRACTED", "source_file": "src/app/predictions/port.py", "source_location": "L8", "weight": 1.0}, {"source": "src_app_predictions_port_py", "target": "port_forecastmodel", "relation": "contains", "confidence": "EXTRACTED", "source_file": "src/app/predictions/port.py", "source_location": "L17", "weight": 1.0}, {"source": "port_forecastmodel", "target": "protocol", "relation": "inherits", "confidence": "EXTRACTED", "source_file": "src/app/predictions/port.py", "source_location": "L17", "weight": 1.0}, {"source": "port_forecastmodel", "target": "port_forecastmodel_fit", "relation": "method", "confidence": "EXTRACTED", "source_file": "src/app/predictions/port.py", "source_location": "L22", "weight": 1.0}, {"source": "port_forecastmodel", "target": "port_forecastmodel_predict_dish_hour", "relation": "method", "confidence": "EXTRACTED", "source_file": "src/app/predictions/port.py", "source_location": "L24", "weight": 1.0}, {"source": "port_rationale_18", "target": "port_forecastmodel", "relation": "rationale_for", "confidence": "EXTRACTED", "source_file": "src/app/predictions/port.py", "source_location": "L18", "weight": 1.0}]}