{"nodes": [{"id": "frontend_src_app_tsx", "label": "App.tsx", "file_type": "code", "source_file": "frontend/src/App.tsx", "source_location": "L1"}, {"id": "app_guarded", "label": "Guarded()", "file_type": "code", "source_file": "frontend/src/App.tsx", "source_location": "L22"}, {"id": "app_app", "label": "App()", "file_type": "code", "source_file": "frontend/src/App.tsx", "source_location": "L27"}], "edges": [{"source": "frontend_src_app_tsx", "target": "react_router_dom", "relation": "imports_from", "confidence": "EXTRACTED", "source_file": "frontend/src/App.tsx", "source_location": "L1", "weight": 1.0}, {"source": "frontend_src_app_tsx", "target": "frontend_src_components_appshell", "relation": "imports_from", "confidence": "EXTRACTED", "source_file": "frontend/src/App.tsx", "source_location": "L2", "weight": 1.0}, {"source": "frontend_src_app_tsx", "target": "frontend_src_components_toaster", "relation": "imports_from", "confidence": "EXTRACTED", "source_file": "frontend/src/App.tsx", "source_location": "L3", "weight": 1.0}, {"source": "frontend_src_app_tsx", "target": "frontend_src_lib_auth", "relation": "imports_from", "confidence": "EXTRACTED", "source_file": "frontend/src/App.tsx", "source_location": "L4", "weight": 1.0}, {"source": "frontend_src_app_tsx", "target": "frontend_src_screens_analyticsscreen", "relation": "imports_from", "confidence": "EXTRACTED", "source_file": "frontend/src/App.tsx", "source_location": "L5", "weight": 1.0}, {"source": "frontend_src_app_tsx", "target": "frontend_src_screens_conversationsscreen", "relation": "imports_from", "confidence": "EXTRACTED", "source_file": "frontend/src/App.tsx", "source_location": "L6", "weight": 1.0}, {"source": "frontend_src_app_tsx", "target": "frontend_src_screens_customerprofilescreen", "relation": "imports_from", "confidence": "EXTRACTED", "source_file": "frontend/src/App.tsx", "source_location": "L7", "weight": 1.0}, {"source": "frontend_src_app_tsx", "target": "frontend_src_screens_customersscreen", "relation": "imports_from", "confidence": "EXTRACTED", "source_file": "frontend/src/App.tsx", "source_location": "L8", "weight": 1.0}, {"source": "frontend_src_app_tsx", "target": "frontend_src_screens_liveopsscreen", "relation": "imports_from", "confidence": "EXTRACTED", "source_file": "frontend/src/App.tsx", "source_location": "L9", "weight": 1.0}, {"source": "frontend_src_app_tsx", "target": "frontend_src_screens_loginscreen", "relation": "imports_from", "confidence": "EXTRACTED", "source_file": "frontend/src/App.tsx", "source_location": "L10", "weight": 1.0}, {"source": "frontend_src_app_tsx", "target": "frontend_src_screens_menumanagerscreen", "relation": "imports_from", "confidence": "EXTRACTED", "source_file": "frontend/src/App.tsx", "source_location": "L11", "weight": 1.0}, {"source": "frontend_src_app_tsx", "target": "frontend_src_screens_neworderscreen", "relation": "imports_from", "confidence": "EXTRACTED", "source_file": "frontend/src/App.tsx", "source_location": "L12", "weight": 1.0}, {"source": "frontend_src_app_tsx", "target": "frontend_src_screens_ordersscreen", "relation": "imports_from", "confidence": "EXTRACTED", "source_file": "frontend/src/App.tsx", "source_location": "L13", "weight": 1.0}, {"source": "frontend_src_app_tsx", "target": "frontend_src_screens_publictrackingscreen", "relation": "imports_from", "confidence": "EXTRACTED", "source_file": "frontend/src/App.tsx", "source_location": "L14", "weight": 1.0}, {"source": "frontend_src_app_tsx", "target": "frontend_src_screens_ridertrackingscreen", "relation": "imports_from", "confidence": "EXTRACTED", "source_file": "frontend/src/App.tsx", "source_location": "L15", "weight": 1.0}, {"source": "frontend_src_app_tsx", "target": "frontend_src_screens_ridersscreen", "relation": "imports_from", "confidence": "EXTRACTED", "source_file": "frontend/src/App.tsx", "source_location": "L16", "weight": 1.0}, {"source": "frontend_src_app_tsx", "target": "frontend_src_screens_marketingscreen", "relation": "imports_from", "confidence": "EXTRACTED", "source_file": "frontend/src/App.tsx", "source_location": "L17", "weight": 1.0}, {"source": "frontend_src_app_tsx", "target": "frontend_src_screens_settingsscreen", "relation": "imports_from", "confidence": "EXTRACTED", "source_file": "frontend/src/App.tsx", "source_location": "L18", "weight": 1.0}, {"source": "frontend_src_app_tsx", "target": "frontend_src_screens_ticketsscreen", "relation": "imports_from", "confidence": "EXTRACTED", "source_file": "frontend/src/App.tsx", "source_location": "L19", "weight": 1.0}, {"source": "frontend_src_app_tsx", "target": "frontend_src_screens_couponsscreen", "relation": "imports_from", "confidence": "EXTRACTED", "source_file": "frontend/src/App.tsx", "source_location": "L20", "weight": 1.0}, {"source": "frontend_src_app_tsx", "target": "app_guarded", "relation": "contains", "confidence": "EXTRACTED", "source_file": "frontend/src/App.tsx", "source_location": "L22", "weight": 1.0}, {"source": "frontend_src_app_tsx", "target": "app_app", "relation": "contains", "confidence": "EXTRACTED", "source_file": "frontend/src/App.tsx", "source_location": "L27", "weight": 1.0}]}